selftest/__init__.py
selftest/__main__.py
selftest/asyncer.py
selftest/binder.py
selftest/diffs.py
selftest/filter.py
selftest/fixtures.py
selftest/integrationtests.py
selftest/levels.py
selftest/mocks.py
selftest/operators.py
selftest/prrint.py
selftest/tester.py
selftest/utils.py
selftest/wildcard.py
selftest/tests/__init__.py
selftest/tests/sub_module_fail.py
selftest/tests/sub_module_ok.py
selftest/tests/temporary_class_namespace.py
selftest/tests/tryout.py
selftest/tests/tryout2.py
selftest-0.5.1.dist-info/licenses/LICENSE
selftest-0.5.1.dist-info/METADATA
selftest-0.5.1.dist-info/WHEEL
selftest-0.5.1.dist-info/entry_points.txt
selftest-0.5.1.dist-info/top_level.txt
selftest-0.5.1.dist-info/RECORD
