Metadata-Version: 2.4
Name: selftest
Version: 0.5.1
Summary: A tool for running in-source unittests for Python
Author-email: Erik Groeneveld <ejgroene@ieee.org>
License-Expression: GPL-3.0-or-later
Project-URL: Homepage, https://github.com/ejgroene/selftest
Keywords: in-source,unittest,testing
Classifier: Development Status :: 5 - Production/Stable
Classifier: Intended Audience :: Developers
Classifier: Topic :: Software Development :: Testing
Classifier: Topic :: Software Development :: Testing :: Unit
Classifier: Programming Language :: Python :: 3
Classifier: Operating System :: OS Independent
Requires-Python: >=3.9
License-File: LICENSE
Dynamic: license-file
